acapy/__init__.py
acapy/acaplib2.py
acapy/cameracontrol.py
acapy/graphicsbox.py
acapy/sample/AreaSensor_color.ini
acapy/sample/AreaSensor_mono.ini
acapy/sample/acapy_callback_sample.py
acapy/sample/acapy_capture_camera_setting.py
acapy/sample/acapy_gige.py
acapy/sample/acapy_simple_grab.py
acapy/sample/acapy_simple_snap.py
acapy/sample/acapy_tkinter_sample.py
acapy/sample/readme.txt
acapy-1.2.0.dist-info/LICENSE.txt
acapy-1.2.0.dist-info/METADATA
acapy-1.2.0.dist-info/WHEEL
acapy-1.2.0.dist-info/top_level.txt
acapy-1.2.0.dist-info/RECORD
