Metadata-Version: 2.1
Name: acapy
Version: 1.2.0
Summary: acapy package (Python bindings for AVALDATA AcapLib2 )
Home-page: https://faq-avaldata.dga.jp/faq_list.html?category=35
Author: AVALDATA
Author-email: 
License: 3-Clause BSD License
Keywords: AVALDATA acapy AcapLib2
Classifier: Development Status :: 5 - Production/Stable
Classifier: License :: OSI Approved :: BSD License
Classifier: Natural Language :: Japanese
Classifier: Operating System :: Microsoft :: Windows :: Windows 10
Classifier: Operating System :: Microsoft :: Windows :: Windows 11
Classifier: Programming Language :: Python :: 3.8
License-File: LICENSE.txt
